mendelai_ipc/__init__.py
mendelai_ipc/ipc.py
mendelai_ipc-0.6.dist-info/METADATA
mendelai_ipc-0.6.dist-info/WHEEL
mendelai_ipc-0.6.dist-info/top_level.txt
mendelai_ipc-0.6.dist-info/RECORD
