Metadata-Version: 2.1
Name: mendelai-ipc
Version: 0.6
Summary: Simple IPC module that supports communicating over stdin/stdout while chunking messages if they are too large
Home-page: https://github.com/mendelhealth/python_ipc
Author: Karim Tarabishy
Author-email: k.eltarabishy@gmail.com
License: UNKNOWN
Platform: UNKNOWN
